djx_websocket/.git/config
djx_websocket/.git/description
djx_websocket/.git/FETCH_HEAD
djx_websocket/.git/HEAD
djx_websocket/.git/hooks/applypatch-msg.sample
djx_websocket/.git/hooks/commit-msg.sample
djx_websocket/.git/hooks/fsmonitor-watchman.sample
djx_websocket/.git/hooks/post-update.sample
djx_websocket/.git/hooks/pre-applypatch.sample
djx_websocket/.git/hooks/pre-commit.sample
djx_websocket/.git/hooks/pre-merge-commit.sample
djx_websocket/.git/hooks/pre-push.sample
djx_websocket/.git/hooks/pre-rebase.sample
djx_websocket/.git/hooks/pre-receive.sample
djx_websocket/.git/hooks/prepare-commit-msg.sample
djx_websocket/.git/hooks/push-to-checkout.sample
djx_websocket/.git/hooks/update.sample
djx_websocket/.git/index
djx_websocket/.git/info/exclude
djx_websocket/.git/logs/HEAD
djx_websocket/.git/logs/refs/heads/main
djx_websocket/.git/logs/refs/remotes/origin/HEAD
djx_websocket/.git/objects/pack/pack-938c2b073f2341a6216c2f48b6a85f5aafa3292a.idx
djx_websocket/.git/objects/pack/pack-938c2b073f2341a6216c2f48b6a85f5aafa3292a.pack
djx_websocket/.git/ORIG_HEAD
djx_websocket/.git/packed-refs
djx_websocket/.git/refs/heads/main
djx_websocket/.git/refs/remotes/origin/HEAD
djx_websocket/__init__.py
djx_websocket/admin.py
djx_websocket/apps.py
djx_websocket/consumers.py
djx_websocket/functions.py
djx_websocket/migrations/0001_initial.py
djx_websocket/migrations/__init__.py
djx_websocket/models.py
djx_websocket/routing.py
djx_websocket/send_notification.py
djx_websocket/serializers/user_socket_serializers.py
djx_websocket/tests.py
djx_websocket/urls.py
djx_websocket/views/user_socket_views.py
djx_websocket-0.2.dist-info/METADATA
djx_websocket-0.2.dist-info/WHEEL
djx_websocket-0.2.dist-info/RECORD
