Metadata-Version: 2.1
Name: djx-websocket
Version: 0.2
Summary: 
Author: nope
Requires-Python: >=3.10,<4.0
Classifier: Programming Language :: Python :: 3
Classifier: Programming Language :: Python :: 3.10
Classifier: Programming Language :: Python :: 3.11
Requires-Dist: channels (>=4.0.0,<5.0.0)
Requires-Dist: channels-redis (>=4.1.0,<5.0.0)
Requires-Dist: djangorestframework (>=3.14.0,<4.0.0)
Requires-Dist: uvicorn[standard] (>=0.24.0.post1,<0.25.0)
